instaui_tdesign/__init__.py
instaui_tdesign/_settings.py
instaui_tdesign/plugin.py
instaui_tdesign/resources.py
instaui_tdesign/setup.py
instaui_tdesign/symbol.py
instaui_tdesign/types.py
instaui_tdesign/version.py
instaui_tdesign/_use_tools/locale.py
instaui_tdesign/cdn/__init__.py
instaui_tdesign/cdn/_cdn.py
instaui_tdesign/components/_base_element.py
instaui_tdesign/components/_icon_param_utils.py
instaui_tdesign/components/_utils.py
instaui_tdesign/components/affix.py
instaui_tdesign/components/alert.py
instaui_tdesign/components/anchor.py
instaui_tdesign/components/auto_complete.py
instaui_tdesign/components/avatar.py
instaui_tdesign/components/back_top.py
instaui_tdesign/components/badge.py
instaui_tdesign/components/breadcrumb.py
instaui_tdesign/components/button.py
instaui_tdesign/components/calendar.py
instaui_tdesign/components/card.py
instaui_tdesign/components/cascader.py
instaui_tdesign/components/checkbox.py
instaui_tdesign/components/collapse.py
instaui_tdesign/components/color_picker.py
instaui_tdesign/components/comment.py
instaui_tdesign/components/config_provider.py
instaui_tdesign/components/date_picker.py
instaui_tdesign/components/descriptions.py
instaui_tdesign/components/dialog.py
instaui_tdesign/components/divider.py
instaui_tdesign/components/drawer.py
instaui_tdesign/components/dropdown.py
instaui_tdesign/components/empty.py
instaui_tdesign/components/form.py
instaui_tdesign/components/grid.py
instaui_tdesign/components/guide.py
instaui_tdesign/components/icon.py
instaui_tdesign/components/image.py
instaui_tdesign/components/image_viewer.py
instaui_tdesign/components/input.py
instaui_tdesign/components/input_adornment.py
instaui_tdesign/components/input_number.py
instaui_tdesign/components/layout.py
instaui_tdesign/components/link.py
instaui_tdesign/components/list.py
instaui_tdesign/components/loadding.py
instaui_tdesign/components/menu.py
instaui_tdesign/components/message.py
instaui_tdesign/components/notification.py
instaui_tdesign-0.6.0.dist-info/METADATA
instaui_tdesign-0.6.0.dist-info/WHEEL
instaui_tdesign-0.6.0.dist-info/licenses/LICENSE
instaui_tdesign-0.6.0.dist-info/RECORD
