Metadata-Version: 2.4
Name: instaui-tdesign
Version: 0.6.0
Summary: InstaUI TDesign
Author-email: CrystalWindSnake <568166495@qq.com>
License-Expression: MIT
License-File: LICENSE
Keywords: TDesign,gui,instaui,ui,web
Requires-Python: <3.14,>=3.10
Requires-Dist: instaui>=0.8.1
Provides-Extra: all
Requires-Dist: instaui[all]; extra == 'all'
Provides-Extra: web
Requires-Dist: instaui[web]; extra == 'web'
Provides-Extra: webview
Requires-Dist: instaui[webview]; extra == 'webview'
